cdk_notify_bucket/__init__.py
cdk_notify_bucket/py.typed
cdk_notify_bucket/_jsii/__init__.py
cdk_notify_bucket/_jsii/cdk-notify-bucket@2.0.1.jsii.tgz
cdk_notify_bucket-2.0.1.dist-info/LICENSE
cdk_notify_bucket-2.0.1.dist-info/METADATA
cdk_notify_bucket-2.0.1.dist-info/WHEEL
cdk_notify_bucket-2.0.1.dist-info/top_level.txt
cdk_notify_bucket-2.0.1.dist-info/RECORD
